ndradex/__init__.py
ndradex/bin/.devcontainer/Dockerfile
ndradex/bin/.devcontainer/devcontainer.json
ndradex/bin/.git
ndradex/bin/.github/workflows/formula.yml
ndradex/bin/.github/workflows/tests.yml
ndradex/bin/.gitignore
ndradex/bin/CITATION.cff
ndradex/bin/Formula/radex.rb
ndradex/bin/LICENSE
ndradex/bin/Makefile
ndradex/bin/README.md
ndradex/consts.py
ndradex/db.py
ndradex/grid.py
ndradex/io.py
ndradex/radex.py
ndradex-0.3.1.dist-info/LICENSE
ndradex-0.3.1.dist-info/METADATA
ndradex-0.3.1.dist-info/WHEEL
ndradex-0.3.1.dist-info/RECORD
